parent_lookup/__init__.py
parent_lookup/lookup.py
parent_lookup/py.typed
parent_lookup/utils/__init__.py
parent_lookup/utils/logging.py
parent_lookup-0.2.0.dist-info/METADATA
parent_lookup-0.2.0.dist-info/WHEEL
parent_lookup-0.2.0.dist-info/licenses/LICENSE
parent_lookup-0.2.0.dist-info/RECORD
