Metadata-Version: 2.4
Name: parent-lookup
Version: 0.2.0
Summary: Python package enabling a child object to dynamically lookup its parent at runtime.
Project-URL: Homepage, https://github.com/ClaasRostock/parent-lookup
Project-URL: Documentation, https://ClaasRostock.github.io/parent-lookup/README.html
Project-URL: Repository, https://github.com/ClaasRostock/parent-lookup.git
Project-URL: Issues, https://github.com/ClaasRostock/parent-lookup/issues
Project-URL: Changelog, https://github.com/ClaasRostock/parent-lookup/blob/main/CHANGELOG.md
Author-email: Claas Rostock <claas.rostock@dnv.com>
Maintainer-email: Claas Rostock <claas.rostock@dnv.com>
License: MIT License
License-File: LICENSE
Keywords: child,lookup,parent
Classifier: Development Status :: 3 - Alpha
Classifier: Environment :: Console
Classifier: Intended Audience :: Developers
Classifier: Intended Audience :: Science/Research
Classifier: License :: OSI Approved :: MIT License
Classifier: Operating System :: MacOS
Classifier: Operating System :: Microsoft :: Windows
Classifier: Operating System :: POSIX :: Linux
Classifier: Programming Language :: Python :: 3.10
Classifier: Programming Language :: Python :: 3.11
Classifier: Programming Language :: Python :: 3.12
Classifier: Programming Language :: Python :: 3.13
Classifier: Topic :: Scientific/Engineering
Classifier: Topic :: Software Development :: Libraries :: Python Modules
Requires-Python: <3.14,>=3.10
Requires-Dist: typing-inspect>=0.9.0
